README.md
setup.py
predstorm/__init__.py
predstorm/data.py
predstorm/plot.py
predstorm/predict.py
predstorm.egg-info/PKG-INFO
predstorm.egg-info/SOURCES.txt
predstorm.egg-info/dependency_links.txt
predstorm.egg-info/top_level.txt
predstorm/config/__init__.py
predstorm/config/constants.py
predstorm/config/plotting.py