Metadata-Version: 2.1
Name: predstorm
Version: 0.1
Summary: UNKNOWN
Home-page: https://github.com/IWF-helio/PREDSTORM
Author: IWF Helio Group
Author-email: christian.moestl@oeaw.ac.at
License: UNKNOWN
Platform: UNKNOWN
Classifier: Programming Language :: Python :: 3
Classifier: License :: OSI Approved :: MIT License
Classifier: Operating System :: OS Independent
